<?xml version="1.0" encoding="ISO-8859-1"?>
<!--
/*      This program is free software; you can redistribute it and/or modify  */
/*       it under the terms of the GNU General Public License as published by */
/*       the Free Software Foundation; either version 2 of the License, or    */
/*       (at your option) any later version.                                  */

/*       This program is distributed in the hope that it will be useful, but  */
/*       WITHOUT ANY WARRANTY; without even the implied warranty of           */
/*       MERCHANTABILITY or FITNESS FOR A PARTICULAR PURPOSE.  See the GNU    */
/*       General Public License for more details.                             */

/*       You should have received a copy of the GNU General Public License    */
/*       along with this program; if not, write to the Free Software          */
/*       Foundation, Inc., 59 Temple Place, Suite 330, Boston, MA  02111-1307 */
/*       USA                                                                  */

/*       Marine Dumousseau                                                    */
/*       EMBL-EBI, neurobiology computational group,                          */
/*       Cambridge, UK. e-mail: marine@ebi.ac.uk                   */
-->

<!--/******************************************************************************/
    	/* contains the parameters for RNA/RNA long bulge loops of ;
	REF: Douglas M Turner et al (2006). Nucleic Acids Research 34: 4912-4924. 
    	REF: Douglas M Turner et al (1999). J.Mol.Biol.  288: 911_940. 
    	/******************************************************************************/-->
    	
    	<data type="long_bulge_loop">
    		<bulge type="initiation" size="1">
    			<enthalpy>10600.0</enthalpy>
    			<entropy>21.9</entropy>
    		</bulge>
    		
    		<bulge type="initiation" size="2">
    			<enthalpy>7100.0</enthalpy>
    			<entropy>13.9</entropy>
    		</bulge>
    		
    		<bulge type="initiation" size="3">
    			<enthalpy>7100.0</enthalpy>
    			<entropy>12.6</entropy>
    		</bulge>
    		
    		<bulge type="initiation" size="4">
    			<enthalpy>7100.0</enthalpy>
    			<entropy>11.3</entropy>
    		</bulge>
    		
    		<bulge type="initiation" size="5">
    			<enthalpy>7100.0</enthalpy>
    			<entropy>10.0</entropy>
    		</bulge>
    		
    		<bulge type="initiation" size="6">
    			<enthalpy>7100.0</enthalpy>
    			<entropy>8.7</entropy>
    		</bulge>
    		
    		<bulge type="initiation" size=">6">
    			<enthalpy>7100.0</enthalpy>
    			<entropy>8.7</entropy>
    		</bulge>
    		
    		<closure type="per_A/U">
 				<enthalpy>5000.0</enthalpy>
 				<entropy>13.9</entropy>
 			</closure>
 			<closure type="per_G/U">
 				<enthalpy>5000.0</enthalpy>
 				<entropy>13.9</entropy>
 			</closure>
    	</data>